onnx_tool/__init__.py
onnx_tool/__main__.py
onnx_tool/fusion.py
onnx_tool/graph.py
onnx_tool/model.py
onnx_tool/node.py
onnx_tool/quantization.py
onnx_tool/serialization.py
onnx_tool/tensor.py
onnx_tool/utils.py
onnx_tool-0.8.5.dist-info/LICENSE
onnx_tool-0.8.5.dist-info/METADATA
onnx_tool-0.8.5.dist-info/WHEEL
onnx_tool-0.8.5.dist-info/top_level.txt
onnx_tool-0.8.5.dist-info/zip-safe
onnx_tool-0.8.5.dist-info/RECORD
