Metadata-Version: 2.1
Name: onnx-tool
Version: 0.8.5
Summary: A tool for ONNX model: A parser, editor and profiler tool for ONNX models.
Home-page: https://github.com/ThanatosShinji/onnx-tool
Author: Luo Yu
Author-email: luoyu888888@gmail.com
License: MIT
Classifier: Programming Language :: Python :: 3
License-File: LICENSE
Requires-Dist: onnx
Requires-Dist: numpy
Requires-Dist: tabulate
